tsdata/__init__.py
tsdata/_loader/__init__.py
tsdata/_loader/as_pandas.py
tsdata/_loader/base.py
tsdata/_version.py
tsdata/fpp3/LakeHuron.csv
tsdata/fpp3/PBS.csv
tsdata/fpp3/__init__.py
tsdata/fpp3/ansett.csv
tsdata/fpp3/aus_accommodation.csv
tsdata/fpp3/aus_airpassengers.csv
tsdata/fpp3/aus_arrivals.csv
tsdata/fpp3/aus_livestock.csv
tsdata/fpp3/aus_production.csv
tsdata/fpp3/aus_retail.csv
tsdata/fpp3/bank_calls.csv
tsdata/fpp3/boston_marathon.csv
tsdata/fpp3/canadian_gas.csv
tsdata/fpp3/gafa_stock.csv
tsdata/fpp3/global_economy.csv
tsdata/fpp3/guinea_rice.csv
tsdata/fpp3/hh_budget.csv
tsdata/fpp3/insurance.csv
tsdata/fpp3/nyc_bikes.csv
tsdata/fpp3/olympic_running.csv
tsdata/fpp3/pedestrian.csv
tsdata/fpp3/pelt.csv
tsdata/fpp3/prices.csv
tsdata/fpp3/prison.csv
tsdata/fpp3/souvenirs.csv
tsdata/fpp3/tourism.csv
tsdata/fpp3/tute1.csv
tsdata/fpp3/us_change.csv
tsdata/fpp3/us_employment.csv
tsdata/fpp3/us_gas_total.csv
tsdata/fpp3/us_gasoline.csv
tsdata/fpp3/vic_elec.csv
tsdata/fpp3/warsaw_air_quality.csv
tsdata/fpppy/AirPassengers.csv
tsdata/fpppy/EPF_FR_BE.csv
tsdata/fpppy/EPF_FR_BE_futr.csv
tsdata/fpppy/EPF_FR_BE_static.csv
tsdata/fpppy/PBS_unparsed.csv
tsdata/fpppy/USAccDeaths.csv
tsdata/fpppy/US_change.csv
tsdata/fpppy/__init__.py
tsdata/fpppy/algeria_exports.csv
tsdata/fpppy/algeria_exports_unparsed.csv
tsdata/fpppy/anscombe.csv
tsdata/fpppy/ansett.csv
tsdata/fpppy/ansett_unparsed.csv
tsdata/fpppy/aus_accomodation.csv
tsdata/fpppy/aus_airpassengers.csv
tsdata/fpppy/aus_arrivals.csv
tsdata/fpppy/aus_economy.csv
tsdata/fpppy/aus_economy_unparsed.csv
tsdata/fpppy/aus_livestock.csv
tsdata/fpppy/aus_production.csv
tsdata/fpppy/aus_production_formatted.csv
tsdata/fpppy/aus_retail.csv
tsdata/fpppy/aus_tourism.csv
tsdata/fpppy/austa.csv
tsdata/fpppy/bank_calls.csv
tsdata/fpppy/boston_marathon.csv
tsdata/fpppy/canadian_gas.csv
tsdata/fpppy/chinese_gdp.csv
tsdata/fpppy/cowtemp.csv
tsdata/fpppy/eggs.csv
tsdata/fpppy/electricity_future_vars.csv
py_tsdata-0.5.0.dist-info/WHEEL
py_tsdata-0.5.0.dist-info/METADATA
py_tsdata-0.5.0.dist-info/RECORD
