Metadata-Version: 2.3
Name: py-tsdata
Version: 0.5.0
Summary: Time Series Datasets
Keywords: time series,data,pandas
Author: NowanIlfideme
Author-email: NowanIlfideme <git@nowan.dev>
License: MIT License
Classifier: Programming Language :: Python :: 3 :: Only
Classifier: License :: OSI Approved :: MIT License
Classifier: Operating System :: OS Independent
Classifier: Development Status :: 5 - Production/Stable
Classifier: Intended Audience :: Developers
Classifier: Topic :: Software Development
Classifier: Typing :: Typed
Requires-Dist: pandas>=2.0.0
Requires-Python: >=3.10
